puckluck/__init__.py
puckluck/nhl.py
puckluck/nicetime.py
puckluck-2023.1.16.2.dist-info/WHEEL
puckluck-2023.1.16.2.dist-info/METADATA
puckluck-2023.1.16.2.dist-info/RECORD
