Metadata-Version: 2.1
Name: puckluck
Version: 2023.1.16.2
Summary: NHL hockey analytics and data collection utilities
Keywords: sports-analytics,NHL,hockey
Author-email: Brock Tibert <btibert3@gmail.com>
Requires-Python: >=3.8
Requires-Dist: requests
Requires-Dist: pandas
Project-URL: Home, https://github.com/Btibert3/puckluck
